customer_analysis/__main__.py
customer_analysis/report_generator.py
customer_analysis_bertollo-0.1.1.dist-info/METADATA
customer_analysis_bertollo-0.1.1.dist-info/WHEEL
customer_analysis_bertollo-0.1.1.dist-info/entry_points.txt
customer_analysis_bertollo-0.1.1.dist-info/top_level.txt
customer_analysis_bertollo-0.1.1.dist-info/RECORD
